arifi_protocol_runner/__init__.py
arifi_protocol_runner/ai_backend.py
arifi_protocol_runner/arifi_protocol_runner.py
arifi_01_protocol_runner-0.2.1.dist-info/METADATA
arifi_01_protocol_runner-0.2.1.dist-info/WHEEL
arifi_01_protocol_runner-0.2.1.dist-info/top_level.txt
arifi_01_protocol_runner-0.2.1.dist-info/RECORD
