Metadata-Version: 2.4
Name: arifi-01-protocol-runner
Version: 0.2.1
Summary: Implementasi PROTOKOL FONDASI: MATRIKS KETERIKATAN Arifi-01
Home-page: https://github.com/razzaqinspires/arifi-01-protocol-runner
Author: Arifi Razzaq
Author-email: "Dr. Profesor Arifi Razzaq" <support@razzaq.dev>
License: MIT
Project-URL: Homepage, https://github.com/razzaqinspires/arifi-01-protocol-runner
Project-URL: Source, https://github.com/razzaqinspires/arifi-01-protocol-runner
Project-URL: Donate, https://saweria.co/arzzq
Requires-Python: >=3.8
Requires-Dist: flake8
Requires-Dist: mypy
Requires-Dist: radon
